behavioral_signals_cli/__init__.py
behavioral_signals_cli/cli.py
behavioral_signals_cli/cliargs.py
behavioral_signals_cli/cmd.py
behavioral_signals_cli/confdict.py
behavioral_signals_cli/frames_csv.py
behavioral_signals_cli/service.py
behavioral_signals_cli/settings.py
behavioral_signals_cli/synth.py
behavioral_signals_cli/utils.py
behavioral_signals_cli-1.10.0.dist-info/AUTHORS.rst
behavioral_signals_cli-1.10.0.dist-info/LICENSE
behavioral_signals_cli-1.10.0.dist-info/METADATA
behavioral_signals_cli-1.10.0.dist-info/WHEEL
behavioral_signals_cli-1.10.0.dist-info/entry_points.txt
behavioral_signals_cli-1.10.0.dist-info/top_level.txt
behavioral_signals_cli-1.10.0.dist-info/RECORD
