Metadata-Version: 2.1
Name: behavioral-signals-cli
Version: 1.10.0
Summary: Command Line Interface for Behavioral Signals Emotion and Behavior Recognition Engine in the Cloud
Home-page: https://bitbucket.org/behavioralsignals/api-cli/src
Author: Behavioral Signals
Author-email: nassos@behavioralsignals.com
License: MIT license
Download-URL: https://bitbucket.org/behavioralsignals/api-cli/get/1.10.0.tar.gz
Keywords: behavioral signals,cli,command line interface,emotion recognition,behavior recognition
Platform: UNKNOWN
Classifier: Development Status :: 5 - Production/Stable
Classifier: Intended Audience :: Developers
Classifier: License :: OSI Approved :: MIT License
Classifier: Natural Language :: English
Classifier: Programming Language :: Python :: 3.6
License-File: LICENSE
License-File: AUTHORS.rst
Requires-Dist: aiofiles (==0.8.0)
Requires-Dist: aiosignal (==1.2.0)
Requires-Dist: aiohttp (==3.8.5)
Requires-Dist: attrs (==22.2.0)
Requires-Dist: async-timeout (==4.0.2)
Requires-Dist: behavioral-signals-swagger-client-3 (==3.11.1)
Requires-Dist: dotmap (==1.3.30)
Requires-Dist: tqdm (==4.64.1)
Requires-Dist: typing-extensions (==4.1.1)
Requires-Dist: ruamel.yaml (==0.17.21)
Requires-Dist: requests (==2.27.1)
Requires-Dist: ratelimit (==2.2.1)
Requires-Dist: yarl (==1.7.2)
Requires-Dist: zipp (==3.6.0)
